{"SNS(를) 하다": [false, true, true, false, true, true, true, true, true], "가족": [true, false, true, true, true, true, false, true, true], "게임": [true, true, true, true, true, true, true], "그래서": [true, true, true, true, true, true, true], "그리고": [true, true, true, true, true, true], "끝나다": [true, true, true, true, true, true, true, true], "농구": [true, true, false, true, true, true, true, true], "뉴스": [true, true, true, true, true, true, true], "늦게": [true, true, true, true, true, true, true], "닦다": [true, true, true, true, true, true, true], "도우미": [true, true, true, true, true, true, false, true], "맥주": [true, true, true, true, true, true, true, true], "면도(를) 하다": [true, true, true, true, true, true, true, false, true], "몇 시": [true, true, true, true, true, true, false, true], "문을 닫다": [true, true, true, true, true, true, true], "보통": [true, true, true, true, true, true, true], "빨래(를) 하다": [true, true, false, true, true, false, true, true, false, false, true], "살다": [true, true, true, true, true, true, true, false, true], "샤워(를) 하다": [false, true, true, true, true, true, true, false, true], "세수(를) 하다": [true, true, true, true, true, true, false, true], "수업": [true, true, true, true, true, true, false, true], "시간": [true, true, true, true, true, true, true], "시작하다": [true, true, true, true, true, true, true, true], "아이": [true, true, false, true, true, true, true, true, true], "아침": [true, true, true, true, true, true, true, true], "아침을 먹다": [true, true, true, true, true, true, true, true], "약속": [true, true, true, true, false, true, true, false, true], "여행": [true, true, true, true, true, true], "여행(을) 하다": [true, true, false, true, true, true, true, true, true], "우리": [true, true, true, true, true, true, true, true], "이": [true, true, true, true, true, true, true, true], "이를 닦다": [true, true, true, true, true, true, true], "이야기(를) 하다": [true, true, true, true, true, false, true], "일기": [true, true, true, true, true, true, true, true], "일기를 쓰다": [false, true, true, true, true, true, true, true, true], "일어나다": [false, true, true, true, true, false, true, false, true, true], "일찍": [true, true, true, true, true, true, true], "저녁": [true, true, true, true, true, true, true], "저녁을 먹다": [true, true, true, true, true, true, true, true], "조금": [true, true, true, true, true, false, true], "쯤": [true, true, true, true, true, true, true], "축제": [true, true, true, true, true, false, true], "친절하다": [false, false, true, true, true, false, true, true, true, true, true, true], "피곤하다": [false, true, true, true, true, true, true, true, true], "화장(을) 하다": [true, true, true, true, true, true, true]}