{
    "Bulgogi": "불고기",
    "Japanese": "일본어",
    "banana": "바나나",
    "classroom": "교실",
    "clothes": "옷",
    "head": "머리",
    "letter": "편지",
    "library": "도서관",
    "light": "불",
    "meal, steamed rice": "밥",
    "milk": "우유",
    "movie": "영화",
    "now": "지금",
    "to be a lot": "많다",
    "to be bad": "나쁘다",
    "to be big": "크다",
    "to be busy": "바쁘다",
    "to be cheap": "싸다",
    "to be clean": "깨끗하다",
    "to be expensive": "비싸다",
    "to be few/little": "적다",
    "to be fun": "재미있다",
    "to be good": "좋다",
    "to be nice": "멋있다",
    "to be pretty": "예쁘다",
    "to be sick": "아프다",
    "to be silent": "조용하다",
    "to be small/little": "작다",
    "to be tasty": "맛있다",
    "to buy": "사다",
    "to clean": "청소(를) 하다",
    "to close": "닫다",
    "to come": "오다",
    "to drink": "마시다",
    "to eat": "먹다",
    "to give": "주다",
    "to go": "가다",
    "to learn": "배우다",
    "to like": "좋아하다",
    "to not taste good": "맛없다",
    "to open": "열다",
    "to read": "읽다",
    "to rest": "쉬다",
    "to see": "보다",
    "to send": "보내다",
    "to sit": "앉다",
    "to stand": "서다",
    "to study": "공부(를) 하다",
    "to teach": "가르치다",
    "to turn off": "끄다",
    "to turn on": "켜다",
    "to wait": "기다리다",
    "to write": "쓰다",
    "weather": "날씨"
}